hello_module/__init__.py
nikitosPackage1-0.0.7.dist-info/METADATA
nikitosPackage1-0.0.7.dist-info/WHEEL
nikitosPackage1-0.0.7.dist-info/entry_points.txt
nikitosPackage1-0.0.7.dist-info/top_level.txt
nikitosPackage1-0.0.7.dist-info/RECORD
